galaxy_workflow_executor-0.2.6.data/scripts/generate_params_from_workflow.py
galaxy_workflow_executor-0.2.6.data/scripts/run_galaxy_workflow.py
wfexecutor/__init__.py
wfexecutor/test_execution_state.py
galaxy_workflow_executor-0.2.6.dist-info/METADATA
galaxy_workflow_executor-0.2.6.dist-info/WHEEL
galaxy_workflow_executor-0.2.6.dist-info/top_level.txt
galaxy_workflow_executor-0.2.6.dist-info/RECORD
