Metadata-Version: 2.1
Name: galaxy-workflow-executor
Version: 0.2.6
Summary: Execute workflows on Galaxy through the CLI
Home-page: UNKNOWN
Author: Suhaib Mohammed, Pablo Moreno
Author-email: 
License: MIT
Platform: UNKNOWN
Requires-Dist: bioblend (==0.13.0)
